halite/__init__.py
halite/data/__init__.py
halite/data/dataloader.py
halite/data/dataset.py
halite/data/index_shuffle.py
halite/data/preprocess.py
halite/data/record.py
halite/data/tokenizers/__init__.py
halite/data/tokenizers/llama3.py
halite/data/tokenizers/sentencepiece.py
halite/distributed/__init__.py
halite/logging/__init__.py
halite/logging/logger.py
halite/nn/__init__.py
halite/nn/activation.py
halite/nn/init.py
halite/nn/loss.py
halite/nn/normalization.py
halite/nn/utils.py
halite/optim/__init__.py
halite/optim/lr_scheduler.py
halite/optim/soap.py
halite/parallel/__init__.py
halite/parallel/fsdp.py
halite/parallel/parallel_dims.py
halite/projects/__init__.py
halite/projects/lm/__init__.py
halite/projects/lm/config.py
halite/transformers/__init__.py
halite/transformers/activation.py
halite/transformers/attention.py
halite/transformers/block.py
halite/transformers/cache_manager.py
halite/transformers/container.py
halite/transformers/convert.py
halite/transformers/embedding.py
halite/transformers/feedforward.py
halite/transformers/generation.py
halite/transformers/initialize.py
halite/transformers/model.py
halite/transformers/normalization.py
halite/transformers/optimizer.py
halite/transformers/parallelize.py
halite/transformers/position.py
halite/transformers/schema.py
halite/transformers/transformer.py
halite/transformers/models/__init__.py
halite/transformers/models/bloom.py
halite/transformers/models/llama.py
halite/transformers/moe/__init__.py
halite/transformers/moe/feedforward.py
halite/transformers/moe/moe.py
halite/transformers/moe/ops.py
halite/transformers/moe/router.py
halite/transformers/moe/token_dispatcher.py
halite/transformers/moe/scattermoe/__init__.py
halite/transformers/moe/scattermoe/kernels.py
halite/transformers/moe/scattermoe/ops.py
halite/transformers/moe/scattermoe/scattermoe.py
halite/transformers/vllm/__init__.py
halite/transformers/vllm/attention.py
halite/transformers/vllm/block.py
halite/transformers/vllm/config.py
halitepy-0.1.0.dist-info/LICENSE
halitepy-0.1.0.dist-info/METADATA
halitepy-0.1.0.dist-info/WHEEL
halitepy-0.1.0.dist-info/top_level.txt
halitepy-0.1.0.dist-info/RECORD
