Metadata-Version: 2.1
Name: halitepy
Version: 0.1.0
Summary: Configuration and distributed training library for PyTorch
Author-email: Kim Seonghyeon <kim.seonghyeon@outlook.com>
License: MIT License
Requires-Python: >=3.7
License-File: LICENSE
Requires-Dist: torch >=2.5
Requires-Dist: rich
Requires-Dist: slickconf
